fincept_terminal/__init__.py
fincept_terminal/assets.py
fincept_terminal/cli.py
fincept_terminal/data.py
fincept_terminal/data_fetcher.py
fincept_terminal/display.py
fincept_terminal/market.py
fincept_terminal/themes.py
fincept_terminal/utilities.py
fincept_investments-0.1.2.dist-info/LICENSE
fincept_investments-0.1.2.dist-info/METADATA
fincept_investments-0.1.2.dist-info/WHEEL
fincept_investments-0.1.2.dist-info/entry_points.txt
fincept_investments-0.1.2.dist-info/top_level.txt
fincept_investments-0.1.2.dist-info/RECORD
