Metadata-Version: 2.1
Name: fincept-investments
Version: 0.1.2
Summary: A Terminal for Financial Market Analysis and Fetching all kinds of Data.
Home-page: https://github.com/Fincept-Corporation/fincept-investments
Author: Fincept Corporation
Author-email: dev@fincept.in
Classifier: Programming Language :: Python :: 3
Classifier: License :: OSI Approved :: MIT License
Classifier: Operating System :: OS Independent
Requires-Python: >=3.6
License-File: LICENSE
Requires-Dist: requests
Requires-Dist: rich
Requires-Dist: gnews
Requires-Dist: click
